Owlcat
