Metadata-Version: 2.4
Name: owlcat
Version: 1.8.0.2
Summary: miscellaneous utility scripts for manipulating radio interferometry data
Home-page: https://github.com/ska-sa/owlcat
Author: Oleg Smirnov
Author-email: Oleg Smirnov <osmirnov@gmail.com>
Requires-Python: >=3.6.0
Requires-Dist: astropy
Requires-Dist: numpy
Requires-Dist: matplotlib
Requires-Dist: python-casacore
Requires-Dist: meqtrees_cattery
Requires-Dist: scipy
Requires-Dist: astro-kittens
Requires-Dist: future-fstrings
Requires-Dist: six
Requires-Dist: future
Requires-Dist: bokeh
Dynamic: author
Dynamic: author-email
Dynamic: home-page
Dynamic: requires-dist
Dynamic: requires-python
Dynamic: summary
